Demineur/__init__.py
Demineur/module1.py
Demineur-0.1.dist-info/LICENSE
Demineur-0.1.dist-info/METADATA
Demineur-0.1.dist-info/WHEEL
Demineur-0.1.dist-info/top_level.txt
Demineur-0.1.dist-info/RECORD
