Metadata-Version: 2.1
Name: Demineur
Version: 0.1
Summary: Réplique du jeu vidéo "Démineur" de Google
Author: Aether-i0n
Author-email: aetherion.github@gmail.com
Classifier: Programming Language :: Python :: 3.8
Classifier: License :: OSI Approved :: MIT License
Classifier: Operating System :: OS Independent
Requires-Python: >=3.8
License-File: LICENSE
Requires-Dist: setuptools==69.2.0
Requires-Dist: wheel
Requires-Dist: twine
